[
    {
        "id": 0,
        "dess": "ir a correr en las mañanas",
        "estado": false
    },
    {
        "id": 1,
        "dess": "Jugar play hasta tarde",
        "estado": false
    },
    {
        "id": 2,
        "dess": "Aprender a manejar avion",
        "estado": false
    },
    {
        "id": 3,
        "dess": "caminar del trabajo hasta mi casa",
        "estado": false
    },
    {
        "id": 4,
        "dess": "correr muy lejos",
        "estado": false
    },
    {
        "id": 5,
        "dess": "pasear al ave",
        "estado": false
    },
    {
        "id": 6,
        "dess": "salir al parque en la madrugada",
        "estado": false
    }
]